geolink2oereb/__init__.py
geolink2oereb/cli.py
geolink2oereb/transform.py
geolink2oereb/lib/__init__.py
geolink2oereb/lib/interfaces/__init__.py
geolink2oereb/lib/interfaces/oerebkrmtrsfr/__init__.py
geolink2oereb/lib/interfaces/oerebkrmtrsfr/v2_0/__init__.py
geolink2oereb/lib/interfaces/oerebkrmtrsfr/v2_0/classes.py
geolink2oereb/lib/interfaces/oerebkrmtrsfr/v2_0/generators.py
geolink2oereb/lib/interfaces/pyramid_oereb/__init__.py
geolink2oereb-0.1.9.dist-info/LICENSE
geolink2oereb-0.1.9.dist-info/METADATA
geolink2oereb-0.1.9.dist-info/WHEEL
geolink2oereb-0.1.9.dist-info/entry_points.txt
geolink2oereb-0.1.9.dist-info/top_level.txt
geolink2oereb-0.1.9.dist-info/RECORD
