Metadata-Version: 2.1
Name: geolink2oereb
Version: 0.1.9
Summary: Transforms a geolink to OeREBKRMtrsfr_V2_0 document entities
Home-page: https://github.com/openoereb/geolink2oereb
Author: Clemens Rudert
Author-email: rudert-geoinformatik@posteo.ch
License: BSD
Keywords: oereb lex geolink formatter html OeREBKRMtrsfr_V2_0
Platform: UNKNOWN
Classifier: Development Status :: 5 - Production/Stable
Classifier: Intended Audience :: Developers
Classifier: License :: OSI Approved :: BSD License
Classifier: Natural Language :: English
Classifier: Operating System :: OS Independent
Classifier: Programming Language :: Python :: 3.10
Classifier: Programming Language :: Python :: 3.11
Classifier: Topic :: Scientific/Engineering :: GIS
Classifier: Topic :: Software Development :: Libraries :: Python Modules
License-File: LICENSE
Provides-Extra: no-version
Requires-Dist: Sphinx ; extra == 'no-version'
Requires-Dist: flake8 ; extra == 'no-version'
Requires-Dist: pluggy ; extra == 'no-version'
Requires-Dist: pyramid-oereb[recommend] ; extra == 'no-version'
Requires-Dist: pytest ; extra == 'no-version'
Requires-Dist: pytest-cov ; extra == 'no-version'
Requires-Dist: requests-mock ; extra == 'no-version'
Requires-Dist: six ; extra == 'no-version'
Requires-Dist: sphinx-rtd-theme ; extra == 'no-version'
Requires-Dist: twine ; extra == 'no-version'
Provides-Extra: recommend
Requires-Dist: Sphinx (==6.2.1) ; extra == 'recommend'
Requires-Dist: flake8 (==6.0.0) ; extra == 'recommend'
Requires-Dist: pluggy (==1.0.0) ; extra == 'recommend'
Requires-Dist: pyramid-oereb[recommend] (==2.4.3) ; extra == 'recommend'
Requires-Dist: pytest-cov (==4.1.0) ; extra == 'recommend'
Requires-Dist: pytest (==7.3.1) ; extra == 'recommend'
Requires-Dist: requests-mock (==1.10.0) ; extra == 'recommend'
Requires-Dist: six (==1.16.0) ; extra == 'recommend'
Requires-Dist: sphinx-rtd-theme (==1.2.1) ; extra == 'recommend'
Requires-Dist: twine (==4.0.2) ; extra == 'recommend'
Provides-Extra: testing
Requires-Dist: WebTest (>=1.3.1) ; extra == 'testing'
Requires-Dist: pytest ; extra == 'testing'
Requires-Dist: pytest-cov ; extra == 'testing'
